[
    
{
    "id": 1,
    "title": "Acode - code editor | FOSS",
    "images": [
        "https://play-lh.googleusercontent.com/tBmfTr_TyGtv24MzhVzW1ajjppSw9KjzunMRBFdxHZ10AmvlEokombjZabATWBuH3lk=w480-h960",
        "https://play-lh.googleusercontent.com/sFEMReDnU2CVc-OnRj1bjSnpIlV8hMxiRfXagM_pnpwi_pkzUIs8b19EO_zLPeGbLZQ=w5120-h2880",
        "https://play-lh.googleusercontent.com/mse025mrQMFXL3thnxSPucASh9kyZnCV6PUGVV3jL3aEJqIvQQCisp_pn98UPcAmp_A=w2560-h1440",
        "https://play-lh.googleusercontent.com/r46QV7RQWBeBsYz6H8tpOapo2lmtfkMnOzr51Hnj2ZeWGOtVrvwK2iJI5esMPFexkg=w5120-h2880",
        "https://play-lh.googleusercontent.com/r46QV7RQWBeBsYz6H8tpOapo2lmtfkMnOzr51Hnj2ZeWGOtVrvwK2iJI5esMPFexkg=w5120-h2880",
        "https://play-lh.googleusercontent.com/JwLENoiqVVNWhqgnDhuqZks9BfzjmghdL5LFrOuoRjFXnWITImvf2P5jxlwrkH_Hgw=w5120-h2880",
        "https://play-lh.googleusercontent.com/afpbW77zPfevuoye0kSgXfp0730pgHEJDxnFl4iUbNtRRCBo_r07i0P2fBbiQNqC4-o=w5120-h2880",
        "https://play-lh.googleusercontent.com/wqOB8BYNzLfufoos5UkOwNrZ-ZDt6mIWSFmLlJSXnqWotXyNdrVuQY_QKiFoO2kYilhf=w2560-h1440",
        "https://play-lh.googleusercontent.com/5Vmz1nQBH3WN3AP6jCdnqfmshppaxnHTRQazL1OmHPxXvazq3_upFs8w7Q_Gcs7oIQ=w2560-h1440"
    ],
    "originalPrice": "2.88",
    "discountedPrice": "0.49",
    "description": "Welcome to Acode!\n\nA powerful, lightweight code editor, and web IDE for Android. Now enhanced with cutting-edge features and updates to transform your coding experience.\n\nWhat's New?\n\nStep into the future of coding with our innovative Plugin System. This brand new feature supports a wide range of plugins, boosting the functionality of Acode to meet all your development needs. With over 30 plugins already available in the Plugin Store, the possibilities are endless.\n\nLatest Updates Include:\n\n- Enhanced Ace Editor: Now updated to version 1.22.0 for more efficient editing.\n- Search in All Files: Our beta feature lets you search and replace text in all files within your opened projects.\n- Customizable Quick Tools: Personalize your quick tools to enhance your workflow.\n- Fast File Listing in Find Files (Ctrl + P): Acode now loads and caches files at startup, leading to faster file listing.\n- Ctrl Key Functionality: Take advantage of keyboard shortcuts for actions such as save (Ctrl+S) and open command palette (Ctrl+Shift+P).\n\nWhy Choose Acode?\n\nAcode lets you build and run websites directly within your browser, debug with ease using the integrated console, and edit a wide range of source files - from Python and CSS to Java, JavaScript, Dart, and more.\n",
    "keyPoints": [
        "Ad-Free Experience: Enjoy a clean, distraction-free coding environment.",
        "Universal File Editor: Edit any file directly from your device.",
        "GitHub Integration: Seamlessly sync your projects with GitHub.",
        "FTP/SFTP Support: Manage your files efficiently with FTP/SFTP.",
        "Extensive Syntax Highlighting: Supports over 100 programming languages.",
        "Personalized Themes: Choose from dozens of unique themes to match your style.",
        "User-Friendly Interface: Navigate with ease through our intuitive design.",
        "In-App Preview: Instantly view your HTML/MarkDown files within the app.",
        "Interactive JavaScript Console: Debug JavaScript code right from the console.",
        "In-App File Browser: Access your files directly within Acode.",
        "Open Source: Benefit from our transparent and community-driven project.",
        "High Performance: Supports files with over 50,000 lines, ensuring smooth workflow.",
        "Multi-File Support: Work on multiple files simultaneously for productive multitasking.",
        "Customizable Interface: Adapt Acode to your personal coding style.",
        "Keyboard Shortcuts: Speed up your coding with handy shortcuts.",
        "File Recovery: Never lose your work with our reliable file recovery feature.",
        "File Management: Keep your projects organized with effective file management."
    ],
    "rating": 4.6,
    "reviews": 935,
    "tag": "premium"
},
    {
    "id": 2,
    "title": "🌙 Ramadan & Eid Special Landing Page",
    "images": [
        "https://i.postimg.cc/wBNym4TF/Screenshot-20250328-074815-Telegram.jpg",
        "https://i.postimg.cc/wj7s6TCC/Screenshot-20250328-074849-Telegram.jpg",
        "https://i.postimg.cc/dtWyPTxR/Screenshot-20250328-074827-Telegram.jpg",
        "https://i.postimg.cc/pd1vPPt6/Screenshot-20250328-082005-Telegram.jpg",
        "https://i.postimg.cc/RZyJqx9N/Screenshot-20250328-075013-Telegram.jpg",
        "https://i.postimg.cc/V6BJ7StC/Screenshot-20250328-075034-Telegram.jpg",
        "https://i.postimg.cc/zB1LSwyN/Screenshot-20250328-075026-Telegram.jpg",
        "https://i.postimg.cc/90mrsWPN/Screenshot-20250328-075040-Telegram.jpg"
    ],
    "originalPrice": "07.99",
    "discountedPrice": "02.99",
    "description": "Introducing a specially designed landing page for Ramadan & Eid, crafted to help you display ads from Adsterra, Monetag, Advertyka, and other ad networks with high conversion rates. This page is fast-loading, SEO-optimized, and mobile-friendly, ensuring maximum traffic and revenue growth during this festive season!\n\n🔹 Why Choose Our Ramadan & Eid Special Landing Page?\n✅ Ramadan & Eid-Themed Design – Engaging festive visuals for better user experience\n✅ High Conversion Optimized – Designed to increase clicks & engagement\n✅ Fast Loading & Mobile-Friendly – Works seamlessly on all devices\n✅ SEO-Optimized – Get organic traffic from search engines\n✅ Supports Multiple Ad Networks – Works perfectly with Adsterra, Monetag, Advertyka, and other CPA & PPC campaigns\n✅ Customizable Design – Easily modify to fit your specific needs\n\n✨ Special Offer: Enjoy exclusive Ramadan & Eid discounts and bonuses – Limited time only!",
    "keyPoints": [
        "Ramadan & Eid Special Landing Page",
        "Ad Network Direct Link Landing Page",
        "High Conversion Optimized Design",
        "Supports Adsterra, Monetag, Advertyka",
        "SEO-Optimized, Fast Loading & Mobile-Friendly",
        "Free domain hosting setup 🙂"
    ],
    "rating": 4.1,
    "reviews": 3002,
    "tag": "new"
},
{
    "id": 3,
    "title": "🌙 Ramadan & Eid Special Landing Page – Coding File ",
    "images": [
        "https://i.postimg.cc/wBNym4TF/Screenshot-20250328-074815-Telegram.jpg",
        "https://i.postimg.cc/wj7s6TCC/Screenshot-20250328-074849-Telegram.jpg",
        "https://i.postimg.cc/dtWyPTxR/Screenshot-20250328-074827-Telegram.jpg",
        "https://i.postimg.cc/pd1vPPt6/Screenshot-20250328-082005-Telegram.jpg",
        "https://i.postimg.cc/RZyJqx9N/Screenshot-20250328-075013-Telegram.jpg",
        "https://i.postimg.cc/V6BJ7StC/Screenshot-20250328-075034-Telegram.jpg",
        "https://i.postimg.cc/zB1LSwyN/Screenshot-20250328-075026-Telegram.jpg",
        "https://i.postimg.cc/90mrsWPN/Screenshot-20250328-075040-Telegram.jpg"
    ],
    "originalPrice": "10.99",
    "discountedPrice": "08.99",
    "description": "Boost your ad network earnings this Ramadan & Eid with our premium landing page template! This fully responsive, high-converting, and SEO-optimized landing page is perfect for displaying Adsterra, Monetag, Advertyka, and other direct link ads. Whether you’re a marketer, developer, or agency, this landing page will help you maximize revenue!\n\n🔹 What You Get with This Landing Page?\n✅ Clean & Well-Structured HTML, CSS & JavaScript Code\n✅ Fully Responsive & Mobile-Friendly Design\n✅ SEO-Optimized for Organic Traffic Growth\n✅ High Conversion Rate for Maximum Earnings\n✅ Fast Loading Speed for Better User Experience\n✅ Compatible with Adsterra, Monetag, Advertyka & More\n✅ Easy Customization – Modify Colors, Fonts & Content Easily\n✅ Ramadan & Eid-Themed UI for Festive Campaigns\n\n✨ 🎁 Special Offer: Get an exclusive Ramadan discount – Limited-time deal!\n",
    "keyPoints": [
        "Ramadan & Eid Landing Page HTML Template",
        "High-Converting Ad Network Landing Page",
        "Fully Responsive & SEO-Optimized Design",
        "Fast, Lightweight & Easy-to-Edit Codebase",
        "Supports Adsterra, Monetag, Advertyka Direct Links"
    ],
    "rating": 5,
    "reviews": 2158,
    "tag": "exclusive"
},
    {
    "id": 4,
    "title": "🕌 Eid Special – Send & Receive Digital Salami with Friends! 🎉",
    "images": [
        "https://i.postimg.cc/rmH0v6m1/Screenshot-20250328-080922-Via.jpg",
        "https://i.postimg.cc/CxC8d6P0/Screenshot-20250328-080929-Via.jpg",
        "https://i.postimg.cc/wB6mNcZm/Screenshot-20250328-080939-Via.jpg",
        "https://i.postimg.cc/jjZJ4nYk/Screenshot-20250328-080953-Via.jpg",
        "https://i.postimg.cc/J0BD8TD9/Screenshot-20250328-081006-Via.jpg",
        "https://i.postimg.cc/4NVPbPLL/Screenshot-20250328-081011-Via.jpg",
        "https://i.postimg.cc/ThMy3rnh/Screenshot-20250328-081021-Via.jpg",
        "https://i.postimg.cc/xjktqnKS/Screenshot-20250328-081028-Via.jpg",
        "https://i.postimg.cc/DwccRZK1/Screenshot-20250328-081108-Via.jpg",
        "https://i.postimg.cc/L8STyPGH/Screenshot-20250328-081118-Via.jpg"
    ],
    "originalPrice": "04.99",
    "discountedPrice": "01.99",
    "description": "Launch your own Eid-special landing page with easy domain & hosting setup! 🖥️ This fully responsive, SEO-optimized, and fast-loading landing page lets users send and receive digital Salami with their friends. 🎁 Create fun challenges, win random Salami, and make Eid celebrations even more exciting!\n\n🔹 Why Choose This Landing Page?\n✅ Easy Domain & Hosting Setup – Run it as your own website\n✅ Interactive Design – Users can send and receive Salami for fun\n✅ Fast Loading & Mobile-Friendly – Works smoothly on all devices\n✅ SEO-Optimized – Gain more traffic and viral reach\n✅ Customizable HTML, CSS & JavaScript Code – Modify and upgrade easily\n✅ High-Conversion Design – Engages users and encourages sharing\n\n✨ 🎁 Special Eid Offer: Get an exclusive discount – Limited-time only!",
    "keyPoints": [
        "Eid Salami Landing Page Template",
        "Fun & Interactive Digital Salami Sharing",
        "SEO-Optimized, Fast Loading & Mobile-Friendly",
        "Fully Customizable Codebase",
        "Supports Easy Domain & Hosting Setup"
    ],
    "rating": 3.9,
    "reviews": 751,
    "tag": "new"
},
{
    "id": 5,
    "title": "🕌 Eid Special – Send & Receive Digital Salami | Full Code Template for Sale! 🎉",
    "images": [
        "https://i.postimg.cc/rmH0v6m1/Screenshot-20250328-080922-Via.jpg",
        "https://i.postimg.cc/CxC8d6P0/Screenshot-20250328-080929-Via.jpg",
        "https://i.postimg.cc/wB6mNcZm/Screenshot-20250328-080939-Via.jpg",
        "https://i.postimg.cc/jjZJ4nYk/Screenshot-20250328-080953-Via.jpg",
        "https://i.postimg.cc/J0BD8TD9/Screenshot-20250328-081006-Via.jpg",
        "https://i.postimg.cc/4NVPbPLL/Screenshot-20250328-081011-Via.jpg",
        "https://i.postimg.cc/ThMy3rnh/Screenshot-20250328-081021-Via.jpg",
        "https://i.postimg.cc/xjktqnKS/Screenshot-20250328-081028-Via.jpg",
        "https://i.postimg.cc/DwccRZK1/Screenshot-20250328-081108-Via.jpg",
        "https://i.postimg.cc/L8STyPGH/Screenshot-20250328-081118-Via.jpg"
    ],
    "originalPrice": "09.99",
    "discountedPrice": "05.99",
    "description": "Transform your Eid celebration with a fully responsive, SEO-optimized landing page that lets users send & receive digital Salami! 🎁 This template is available for purchase with easy domain & hosting setup instructions to help you get started immediately.\n\n🌟 Why Purchase This Template?\n\n✅ Fully Functional Code – Ready to use for sending & receiving Salami\n✅ Easy to Setup – Detailed instructions for domain & hosting setup\n✅ Customizable – Tailor the design and functionality to your needs\n✅ No Need for Extensive Development – Just plug in your domain and hosting, and you're ready to go!\n✅ Fun & Interactive Design – Engage your audience with a unique, Eid-themed experience\n\nReady to start your own digital Salami platform? Buy this full code package and begin right away! 🎉",
    "keyPoints": [
        "Complete HTML, CSS, & JavaScript Code – Fully functional and easy to customize",
        "Responsive Design – Optimized for desktops, tablets, and mobile devices",
        "SEO-Optimized – Ensure better visibility on search engines",
        "Fast Loading Speed – Smooth user experience on all devices",
        "Interactive & Fun Features – Users can engage in Salami challenges, send Salami to friends, and more!",
        "Easy Domain & Hosting Setup – Step-by-step instructions to help you set up your own site in minutes",
        "Customizable – Modify colors, fonts, images, and content as needed",
        "Perfect for Developers, Marketers, & Agencies – Whether you’re building for clients or your own project, this template is a great foundation"
    ],
    "rating": 4.1,
    "reviews": 530,
    "tag": "sale"
}
    
    
]
