[
    
{
    "id": 1,
    "title": "Acode - code editor | FOSS",
    "images": [
        "https://play-lh.googleusercontent.com/tBmfTr_TyGtv24MzhVzW1ajjppSw9KjzunMRBFdxHZ10AmvlEokombjZabATWBuH3lk=w480-h960",
        "https://play-lh.googleusercontent.com/sFEMReDnU2CVc-OnRj1bjSnpIlV8hMxiRfXagM_pnpwi_pkzUIs8b19EO_zLPeGbLZQ=w5120-h2880",
        "https://play-lh.googleusercontent.com/mse025mrQMFXL3thnxSPucASh9kyZnCV6PUGVV3jL3aEJqIvQQCisp_pn98UPcAmp_A=w2560-h1440",
        "https://play-lh.googleusercontent.com/r46QV7RQWBeBsYz6H8tpOapo2lmtfkMnOzr51Hnj2ZeWGOtVrvwK2iJI5esMPFexkg=w5120-h2880",
        "https://play-lh.googleusercontent.com/r46QV7RQWBeBsYz6H8tpOapo2lmtfkMnOzr51Hnj2ZeWGOtVrvwK2iJI5esMPFexkg=w5120-h2880",
        "https://play-lh.googleusercontent.com/JwLENoiqVVNWhqgnDhuqZks9BfzjmghdL5LFrOuoRjFXnWITImvf2P5jxlwrkH_Hgw=w5120-h2880",
        "https://play-lh.googleusercontent.com/afpbW77zPfevuoye0kSgXfp0730pgHEJDxnFl4iUbNtRRCBo_r07i0P2fBbiQNqC4-o=w5120-h2880",
        "https://play-lh.googleusercontent.com/wqOB8BYNzLfufoos5UkOwNrZ-ZDt6mIWSFmLlJSXnqWotXyNdrVuQY_QKiFoO2kYilhf=w2560-h1440",
        "https://play-lh.googleusercontent.com/5Vmz1nQBH3WN3AP6jCdnqfmshppaxnHTRQazL1OmHPxXvazq3_upFs8w7Q_Gcs7oIQ=w2560-h1440"
    ],
    "originalPrice": "02.88",
    "discountedPrice": "0.49",
    "description": "Welcome to Acode!\n\nA powerful, lightweight code editor, and web IDE for Android. Now enhanced with cutting-edge features and updates to transform your coding experience.\n\nWhat's New?\n\nStep into the future of coding with our innovative Plugin System. This brand new feature supports a wide range of plugins, boosting the functionality of Acode to meet all your development needs. With over 30 plugins already available in the Plugin Store, the possibilities are endless.\n\nLatest Updates Include:\n\n- Enhanced Ace Editor: Now updated to version 1.22.0 for more efficient editing.\n- Search in All Files: Our beta feature lets you search and replace text in all files within your opened projects.\n- Customizable Quick Tools: Personalize your quick tools to enhance your workflow.\n- Fast File Listing in Find Files (Ctrl + P): Acode now loads and caches files at startup, leading to faster file listing.\n- Ctrl Key Functionality: Take advantage of keyboard shortcuts for actions such as save (Ctrl+S) and open command palette (Ctrl+Shift+P).\n\nWhy Choose Acode?\n\nAcode lets you build and run websites directly within your browser, debug with ease using the integrated console, and edit a wide range of source files - from Python and CSS to Java, JavaScript, Dart, and more.\n",
    "keyPoints": [
        "Ad-Free Experience: Enjoy a clean, distraction-free coding environment.",
        "Universal File Editor: Edit any file directly from your device.",
        "GitHub Integration: Seamlessly sync your projects with GitHub.",
        "FTP/SFTP Support: Manage your files efficiently with FTP/SFTP.",
        "Extensive Syntax Highlighting: Supports over 100 programming languages.",
        "Personalized Themes: Choose from dozens of unique themes to match your style.",
        "User-Friendly Interface: Navigate with ease through our intuitive design.",
        "In-App Preview: Instantly view your HTML/MarkDown files within the app.",
        "Interactive JavaScript Console: Debug JavaScript code right from the console.",
        "In-App File Browser: Access your files directly within Acode.",
        "Open Source: Benefit from our transparent and community-driven project.",
        "High Performance: Supports files with over 50,000 lines, ensuring smooth workflow.",
        "Multi-File Support: Work on multiple files simultaneously for productive multitasking.",
        "Customizable Interface: Adapt Acode to your personal coding style.",
        "Keyboard Shortcuts: Speed up your coding with handy shortcuts.",
        "File Recovery: Never lose your work with our reliable file recovery feature.",
        "File Management: Keep your projects organized with effective file management."
    ],
    "rating": 4.6,
    "reviews": 935,
    "tag": "premium"
},
    {
    "id": 2,
    "title": "🌙 Ramadan & Eid Special Landing Page",
    "images": [
        "https://i.postimg.cc/wBNym4TF/Screenshot-20250328-074815-Telegram.jpg",
        "https://i.postimg.cc/wj7s6TCC/Screenshot-20250328-074849-Telegram.jpg",
        "https://i.postimg.cc/dtWyPTxR/Screenshot-20250328-074827-Telegram.jpg",
        "https://i.postimg.cc/pd1vPPt6/Screenshot-20250328-082005-Telegram.jpg",
        "https://i.postimg.cc/RZyJqx9N/Screenshot-20250328-075013-Telegram.jpg",
        "https://i.postimg.cc/V6BJ7StC/Screenshot-20250328-075034-Telegram.jpg",
        "https://i.postimg.cc/zB1LSwyN/Screenshot-20250328-075026-Telegram.jpg",
        "https://i.postimg.cc/90mrsWPN/Screenshot-20250328-075040-Telegram.jpg"
    ],
    "originalPrice": "07.99",
    "discountedPrice": "02.99",
    "description": "Introducing a specially designed landing page for Ramadan & Eid, crafted to help you display ads from Adsterra, Monetag, Advertyka, and other ad networks with high conversion rates. This page is fast-loading, SEO-optimized, and mobile-friendly, ensuring maximum traffic and revenue growth during this festive season!\n\n🔹 Why Choose Our Ramadan & Eid Special Landing Page?\n✅ Ramadan & Eid-Themed Design – Engaging festive visuals for better user experience\n✅ High Conversion Optimized – Designed to increase clicks & engagement\n✅ Fast Loading & Mobile-Friendly – Works seamlessly on all devices\n✅ SEO-Optimized – Get organic traffic from search engines\n✅ Supports Multiple Ad Networks – Works perfectly with Adsterra, Monetag, Advertyka, and other CPA & PPC campaigns\n✅ Customizable Design – Easily modify to fit your specific needs\n\n✨ Special Offer: Enjoy exclusive Ramadan & Eid discounts and bonuses – Limited time only!",
    "keyPoints": [
        "Ramadan & Eid Special Landing Page",
        "Ad Network Direct Link Landing Page",
        "High Conversion Optimized Design",
        "Supports Adsterra, Monetag, Advertyka",
        "SEO-Optimized, Fast Loading & Mobile-Friendly",
        "Free domain hosting setup 🙂"
    ],
    "rating": 4.1,
    "reviews": 3002,
    "tag": "new"
},
{
    "id": 3,
    "title": "🌙 Ramadan & Eid Special Landing Page – Coding File ",
    "images": [
        "https://i.postimg.cc/wBNym4TF/Screenshot-20250328-074815-Telegram.jpg",
        "https://i.postimg.cc/wj7s6TCC/Screenshot-20250328-074849-Telegram.jpg",
        "https://i.postimg.cc/dtWyPTxR/Screenshot-20250328-074827-Telegram.jpg",
        "https://i.postimg.cc/pd1vPPt6/Screenshot-20250328-082005-Telegram.jpg",
        "https://i.postimg.cc/RZyJqx9N/Screenshot-20250328-075013-Telegram.jpg",
        "https://i.postimg.cc/V6BJ7StC/Screenshot-20250328-075034-Telegram.jpg",
        "https://i.postimg.cc/zB1LSwyN/Screenshot-20250328-075026-Telegram.jpg",
        "https://i.postimg.cc/90mrsWPN/Screenshot-20250328-075040-Telegram.jpg"
    ],
    "originalPrice": "10.99",
    "discountedPrice": "08.99",
    "description": "Boost your ad network earnings this Ramadan & Eid with our premium landing page template! This fully responsive, high-converting, and SEO-optimized landing page is perfect for displaying Adsterra, Monetag, Advertyka, and other direct link ads. Whether you’re a marketer, developer, or agency, this landing page will help you maximize revenue!\n\n🔹 What You Get with This Landing Page?\n✅ Clean & Well-Structured HTML, CSS & JavaScript Code\n✅ Fully Responsive & Mobile-Friendly Design\n✅ SEO-Optimized for Organic Traffic Growth\n✅ High Conversion Rate for Maximum Earnings\n✅ Fast Loading Speed for Better User Experience\n✅ Compatible with Adsterra, Monetag, Advertyka & More\n✅ Easy Customization – Modify Colors, Fonts & Content Easily\n✅ Ramadan & Eid-Themed UI for Festive Campaigns\n\n✨ 🎁 Special Offer: Get an exclusive Ramadan discount – Limited-time deal!\n",
    "keyPoints": [
        "Ramadan & Eid Landing Page HTML Template",
        "High-Converting Ad Network Landing Page",
        "Fully Responsive & SEO-Optimized Design",
        "Fast, Lightweight & Easy-to-Edit Codebase",
        "Supports Adsterra, Monetag, Advertyka Direct Links"
    ],
    "rating": 5,
    "reviews": 2158,
    "tag": "exclusive"
},
    {
    "id": 4,
    "title": "🕌 Eid Special – Send & Receive Digital Salami with Friends! 🎉",
    "images": [
        "https://i.postimg.cc/rmH0v6m1/Screenshot-20250328-080922-Via.jpg",
        "https://i.postimg.cc/CxC8d6P0/Screenshot-20250328-080929-Via.jpg",
        "https://i.postimg.cc/wB6mNcZm/Screenshot-20250328-080939-Via.jpg",
        "https://i.postimg.cc/jjZJ4nYk/Screenshot-20250328-080953-Via.jpg",
        "https://i.postimg.cc/J0BD8TD9/Screenshot-20250328-081006-Via.jpg",
        "https://i.postimg.cc/4NVPbPLL/Screenshot-20250328-081011-Via.jpg",
        "https://i.postimg.cc/ThMy3rnh/Screenshot-20250328-081021-Via.jpg",
        "https://i.postimg.cc/xjktqnKS/Screenshot-20250328-081028-Via.jpg",
        "https://i.postimg.cc/DwccRZK1/Screenshot-20250328-081108-Via.jpg",
        "https://i.postimg.cc/L8STyPGH/Screenshot-20250328-081118-Via.jpg"
    ],
    "originalPrice": "04.99",
    "discountedPrice": "01.99",
    "description": "Launch your own Eid-special landing page with easy domain & hosting setup! 🖥️ This fully responsive, SEO-optimized, and fast-loading landing page lets users send and receive digital Salami with their friends. 🎁 Create fun challenges, win random Salami, and make Eid celebrations even more exciting!\n\n🔹 Why Choose This Landing Page?\n✅ Easy Domain & Hosting Setup – Run it as your own website\n✅ Interactive Design – Users can send and receive Salami for fun\n✅ Fast Loading & Mobile-Friendly – Works smoothly on all devices\n✅ SEO-Optimized – Gain more traffic and viral reach\n✅ Customizable HTML, CSS & JavaScript Code – Modify and upgrade easily\n✅ High-Conversion Design – Engages users and encourages sharing\n\n✨ 🎁 Special Eid Offer: Get an exclusive discount – Limited-time only!",
    "keyPoints": [
        "Eid Salami Landing Page Template",
        "Fun & Interactive Digital Salami Sharing",
        "SEO-Optimized, Fast Loading & Mobile-Friendly",
        "Fully Customizable Codebase",
        "Supports Easy Domain & Hosting Setup"
    ],
    "rating": 3.9,
    "reviews": 751,
    "tag": "new"
},
{
    "id": 5,
    "title": "🕌 Eid Special – Send & Receive Digital Salami | Full Code Template for Sale! 🎉",
    "images": [
        "https://i.postimg.cc/rmH0v6m1/Screenshot-20250328-080922-Via.jpg",
        "https://i.postimg.cc/CxC8d6P0/Screenshot-20250328-080929-Via.jpg",
        "https://i.postimg.cc/wB6mNcZm/Screenshot-20250328-080939-Via.jpg",
        "https://i.postimg.cc/jjZJ4nYk/Screenshot-20250328-080953-Via.jpg",
        "https://i.postimg.cc/J0BD8TD9/Screenshot-20250328-081006-Via.jpg",
        "https://i.postimg.cc/4NVPbPLL/Screenshot-20250328-081011-Via.jpg",
        "https://i.postimg.cc/ThMy3rnh/Screenshot-20250328-081021-Via.jpg",
        "https://i.postimg.cc/xjktqnKS/Screenshot-20250328-081028-Via.jpg",
        "https://i.postimg.cc/DwccRZK1/Screenshot-20250328-081108-Via.jpg",
        "https://i.postimg.cc/L8STyPGH/Screenshot-20250328-081118-Via.jpg"
    ],
    "originalPrice": "09.99",
    "discountedPrice": "05.99",
    "description": "Transform your Eid celebration with a fully responsive, SEO-optimized landing page that lets users send & receive digital Salami! 🎁 This template is available for purchase with easy domain & hosting setup instructions to help you get started immediately.\n\n🌟 Why Purchase This Template?\n\n✅ Fully Functional Code – Ready to use for sending & receiving Salami\n✅ Easy to Setup – Detailed instructions for domain & hosting setup\n✅ Customizable – Tailor the design and functionality to your needs\n✅ No Need for Extensive Development – Just plug in your domain and hosting, and you're ready to go!\n✅ Fun & Interactive Design – Engage your audience with a unique, Eid-themed experience\n\nReady to start your own digital Salami platform? Buy this full code package and begin right away! 🎉",
    "keyPoints": [
        "Complete HTML, CSS, & JavaScript Code – Fully functional and easy to customize",
        "Responsive Design – Optimized for desktops, tablets, and mobile devices",
        "SEO-Optimized – Ensure better visibility on search engines",
        "Fast Loading Speed – Smooth user experience on all devices",
        "Interactive & Fun Features – Users can engage in Salami challenges, send Salami to friends, and more!",
        "Easy Domain & Hosting Setup – Step-by-step instructions to help you set up your own site in minutes",
        "Customizable – Modify colors, fonts, images, and content as needed",
        "Perfect for Developers, Marketers, & Agencies – Whether you’re building for clients or your own project, this template is a great foundation"
    ],
    "rating": 4.1,
    "reviews": 530,
    "tag": "sale"
},
    
{
    "id": 6,
    "title": "🚀 Modern Job Offer Landing Page – Attract & Convert More Job Seekers!",
    "images": [
        "https://i.postimg.cc/L6KQ39wt/Screenshot-20250328-164131-Telegram.jpg",
        "https://i.postimg.cc/tT8SfpTH/Screenshot-20250328-164137-Telegram.jpg",
        "https://i.postimg.cc/qBCZKhbB/Screenshot-20250328-164144-Telegram.jpg",
        "https://i.postimg.cc/FzcWX8dk/Screenshot-20250328-164153-Telegram.jpg",
        "https://i.postimg.cc/CLGPPypW/Screenshot-20250328-164201-Telegram.jpg",
        "https://link-virid-five.vercel.app/GIF_20250328_01.gif"
    ],
    "originalPrice": "08.99",
    "discountedPrice": "02.99",
    "description": "Looking for a high-converting, SEO-friendly, and modern job offer landing page? Our unique and stylishly designed landing page is perfect for sharing job opportunities in an eye-catching and user-friendly way! Whether you're running a job board, recruitment agency, or career platform, this landing page will help you engage job seekers instantly and increase conversions.\n\n🔹 Why Choose This Job Offer Landing Page?\n✅ Modern & Unique Design – Stand out from competitors with a sleek, professional look\n✅ SEO-Optimized – Rank higher on search engines and attract organic traffic\n✅ Fast Loading & Mobile-Friendly – Ensures a smooth experience on all devices\n✅ High Conversion Rate – Designed to capture attention and drive applications\n✅ Easy Job Listing Management – Share job offers effortlessly\n✅ Customizable Layout – Adjust colors, fonts, and sections to match your brand\n✅ Built for Engagement – Keep users interested with an intuitive UI\n\n✨ 🎁 Special Offer: Get an exclusive discount – Limited-time deal!\n",
    "keyPoints": [
        "Job Offer Landing Page Template",
        "Modern & Professional Job Board",
        "SEO-Optimized & High-Converting",
        "Fully Responsive & Mobile-Friendly",
        "fully setup domain and hosting no extra charge"
    ],
    "rating": 4.9,
    "reviews": 709,
    "tag": "popular"
},
{
    "id": 7,
    "title": "🚀 Job Offer Landing Page – Full Code Template for Sale!",
    "images": [
        "https://i.postimg.cc/L6KQ39wt/Screenshot-20250328-164131-Telegram.jpg",
        "https://link-virid-five.vercel.app/GIF_20250328_01.gif",
        "https://i.postimg.cc/qBCZKhbB/Screenshot-20250328-164144-Telegram.jpg",
        "https://i.postimg.cc/FzcWX8dk/Screenshot-20250328-164153-Telegram.jpg",
        "https://i.postimg.cc/CLGPPypW/Screenshot-20250328-164201-Telegram.jpg",
        "https://i.postimg.cc/tT8SfpTH/Screenshot-20250328-164137-Telegram.jpg"
    ],
    "originalPrice": "12.49",
    "discountedPrice": "05.49",
    "description": "Boost your recruitment game with this modern, SEO-friendly, and high-converting job offer landing page! 🏆 Designed to attract job seekers quickly, this fully responsive template is perfect for job boards, recruitment agencies, and career platforms. Now available as a complete coding package, ready for customization and deployment!\n\n🔹 What’s Included in the Code Package?\n✅ Complete HTML, CSS & JavaScript Code – Fully functional and easy to customize\n✅ Modern & Unique Design – Sleek, professional, and engaging UI\n✅ SEO-Optimized – Helps rank higher on search engines\n✅ Fast Loading & Mobile-Friendly – Ensures a smooth experience on all devices\n✅ High Conversion Rate – Designed to capture attention and drive applications\n✅ Easy Job Listing Management – Simple structure for adding job posts\n✅ Customizable Layout – Modify colors, fonts, and sections effortlessly\n✅ Perfect for Developers, Marketers & Agencies – Ideal for launching job platforms quickly\n\n✨ 🎁 Special Offer: Get an exclusive discount – Limited-time only!",
    "keyPoints": [
        "Ready-to-Use Job Listing Landing Page",
        "Fully Customizable & Developer-Friendly Code",
        "SEO, Fast Loading & High Engagement Design",
        "Easy Domain & Hosting Setup Guide Included",
        "Customizable HTML, CSS & JavaScript Code"
    ],
    "rating": 4.6,
    "reviews": 807,
    "tag": "exclusive"
},
    {
    "id": 8,
    "title": "🎰 Lucky Number Bonus Game – High-Converting Landing Page for Sale!",
    "images": [
        "https://i.postimg.cc/76jrTkcX/Screenshot-20250329-123017-Spck-Node-JS.jpg",
        "https://i.postimg.cc/W3dP339h/Screenshot-20250329-123023-Spck-Node-JS.jpg",
        "https://i.postimg.cc/tJPQ3cGb/Screenshot-20250329-123102-Spck-Node-JS.jpg",
        "https://i.postimg.cc/bvChpb97/Screenshot-20250329-123107-Spck-Node-JS.jpg"
    ],
    "originalPrice": "04.99",
    "discountedPrice": "0.99",
    "description": "Launch your own gaming platform with our premium, high-converting Lucky Number Bonus Game landing page! 🚀 This unique and professionally designed page comes with FREE lifetime domain & hosting—no monthly fees, no hidden charges! 🎁\n\nThis landing page is built to attract maximum user engagement with a sleek modern UI, premium graphics, and high-speed performance. Perfect for gaming entrepreneurs, marketers, and affiliates looking to drive conversions effortlessly.\n\n🔹 Why Choose This Landing Page?\n✅ FREE Lifetime Domain & Hosting – No extra charges, ever!\n✅ 100% Unique & Eye-Catching Design – High-quality visuals and advanced UI/UX\n✅ High-Converting Layout – Designed to boost sign-ups & engagement\n✅ SEO-Optimized & Fast Loading – Rank higher and attract organic traffic\n✅ Fully Responsive & Mobile-Friendly – Works perfectly on all devices\n✅ Easy One-Click Setup – No coding skills required!\n✅ No Monthly Fees or Extra Charges – Pay once, enjoy forever\n✅ Perfect for Marketers, Affiliates & Entrepreneurs – Monetize with ease\n\n✨ 🎁 Special Offer: Get this premium Lucky Number Bonus Game landing page with FREE domain & hosting for life!",
    "keyPoints": [
        "Lucky Number Bonus Game Landing Page",
        "FREE Lifetime Domain & Hosting Included",
        "SEO-Optimized, High-Speed & Mobile-Friendly",
        "Unique, High-Converting, & Professional Design",
        "No Monthly Fees – One-Time Purchase"
    ],
    "rating": 5,
    "reviews": 1890,
    "tag": "exclusive"
},
{
    "id": 9,
    "title": "🎰 Lucky Number Bonus Game – Full Code Template for Sale!",
    "images": [
        "https://i.postimg.cc/76jrTkcX/Screenshot-20250329-123017-Spck-Node-JS.jpg",
        "https://i.postimg.cc/W3dP339h/Screenshot-20250329-123023-Spck-Node-JS.jpg",
        "https://i.postimg.cc/tJPQ3cGb/Screenshot-20250329-123102-Spck-Node-JS.jpg",
        "https://i.postimg.cc/bvChpb97/Screenshot-20250329-123107-Spck-Node-JS.jpg"
    ],
    "originalPrice": "09.49",
    "discountedPrice": "05.99",
    "description": "Get your hands on a high-converting, premium Lucky Number Bonus Game landing page! 🚀 This fully responsive and SEO-optimized template is designed with stunning graphics, modern UI, and fast-loading performance to maximize user engagement. Now available as a complete coding package—fully customizable and ready for deployment!\n\nThis is a one-time purchase with no recurring fees, allowing you to modify and use it as per your needs. Perfect for developers, marketers, and entrepreneurs looking for a professional-grade landing page to boost conversions!\n\n🔹 What’s Included in the Code Package?\n✅ Complete HTML, CSS & JavaScript Code – Clean, structured, and fully customizable\n✅ Modern & High-Quality Graphics – Unique, eye-catching UI for maximum engagement\n✅ SEO-Optimized & Fast Loading – Ensures better ranking and user experience\n✅ 100% Responsive & Mobile-Friendly – Works smoothly on all devices\n✅ High-Converting Layout – Optimized for better sign-ups & user retention\n✅ Easy Integration & Setup – No complicated configurations required\n✅ No Monthly Fees – One-Time Purchase – Buy once, use forever\n✅ Fully Customizable – Modify design, features, and content as per your needs\n\n✨ 🎁 Special Offer: Get this Lucky Number Bonus Game landing page code at an exclusive discount – limited-time deal!",
    "keyPoints": [
        "Lucky Number Bonus Game Landing Page Code",
        "Fully Responsive & High-Converting UI/UX",
        "SEO-Optimized, Fast-Loading & Mobile-Friendly",
        "Customizable HTML, CSS & JavaScript",
        "One-Time Purchase – No Monthly Fees"
    ],
    "rating": 5,
    "reviews": 908,
    "tag": "hot"
},
    {
    "id": 10,
    "title": "📱 High CPM Android App – Earn More with Direct Ad Links! 🚀",
    "images": [
        "https://i.postimg.cc/pX4P43BD/Screenshot-20250329-140353.jpg",
        "https://i.postimg.cc/7ZzqkXBj/Screenshot-20250329-140431.jpg",
        "https://i.postimg.cc/mk6TbnWW/Screenshot-20250329-140222.jpg",
        "https://i.postimg.cc/hPfSCKVD/Screenshot-20250329-140401.jpg",
        "https://i.postimg.cc/RCPSQW6p/Screenshot-20250329-140409.jpg",
        "https://i.postimg.cc/FKQNsc8z/Screenshot-20250329-140455.jpg"
    ],
    "originalPrice": "10.99",
    "discountedPrice": "02.99",
    "description": "Maximize your ad revenue with our High CPM Android App! 🎯 This self-click earning app allows you to manage and monetize direct ad network links efficiently. With ultra-high CPM rates, you can boost your earnings effortlessly by directing traffic to premium ad networks.\n\nThis app is perfect for marketers, affiliates, and ad network professionals who want to optimize their campaigns and generate higher revenue without hassle.\n\n🔹 Why Choose This High CPM App?\n✅ Self-Click Earning System – Monetize direct ad links effortlessly\n✅ Ultra-High CPM Rates – Get maximum earnings per click\n✅ Fully Optimized for Ad Networks – Works with multiple direct link providers\n✅ Fast, Secure & Reliable – Built with smooth performance and security in mind\n✅ User-Friendly Interface – Easy to navigate and manage campaigns\n✅ No Extra Charges – One-Time Purchase – Buy once, earn unlimited!\n✅ Ready for Instant Deployment – Download, set up, and start earning\n\n✨ 📌 How to Order?\n🔹 Direct Order Available! Click here: https://cpm.tgapps.site/\n🔹 Watch the App Demo Video and learn more before you buy!",
    "keyPoints": [
        "High CPM Earning App for Android",
        "Monetize Direct Ad Network Links",
        "Fast, Secure & User-Friendly",
        "One-Time Purchase – No Monthly Fees",
        "Perfect for Marketers & Affiliates"
    ],
    "rating": 4.7,
    "reviews": 1789,
    "tag": "popular"
}
]
